{"lastUsed":1592212949598,"path":"C:\/src\/jspwork","projectCount":2,"recentFiles":[{"path":"\/work1\/WebContent\/WEB-INF","parentWorkspace":"C:\/src\/jspwork","name":"web.xml","lastModified":1592198957171,"locationURI":"file:\/C:\/src\/jspwork\/work1\/WebContent\/WEB-INF\/web.xml"},{"path":"\/work1","parentWorkspace":"C:\/src\/jspwork","name":"README.md","lastModified":1592198885200,"locationURI":"file:\/C:\/src\/jspwork\/work1\/README.md"},{"path":"\/work1\/WebContent\/product","parentWorkspace":"C:\/src\/jspwork","name":"Ver1.jsp","lastModified":1592210177452,"locationURI":"file:\/C:\/src\/jspwork\/work1\/WebContent\/product\/Ver1.jsp"},{"path":"\/work1\/src\/com\/base\/work\/action\/product","parentWorkspace":"C:\/src\/jspwork","name":"ProductHomeAction.java","lastModified":1592202738826,"locationURI":"file:\/C:\/src\/jspwork\/work1\/src\/com\/base\/work\/action\/product\/ProductHomeAction.java"},{"path":"\/work1\/WebContent\/js","parentWorkspace":"C:\/src\/jspwork","name":"ver1.js","lastModified":1592212639827,"locationURI":"file:\/C:\/src\/jspwork\/work1\/WebContent\/js\/ver1.js"},{"path":"\/work1\/WebContent\/test","parentWorkspace":"C:\/src\/jspwork","name":"dbConnTest.jsp","lastModified":1592199387716,"locationURI":"file:\/C:\/src\/jspwork\/work1\/WebContent\/test\/dbConnTest.jsp"},{"path":"\/work1\/src\/com\/base\/work\/model","parentWorkspace":"C:\/src\/jspwork","name":"Product.java","lastModified":1592199657562,"locationURI":"file:\/C:\/src\/jspwork\/work1\/src\/com\/base\/work\/model\/Product.java"},{"path":"\/work1\/src\/com\/base\/work\/action\/product","parentWorkspace":"C:\/src\/jspwork","name":"ProductSortAction.java","lastModified":1592212759867,"locationURI":"file:\/C:\/src\/jspwork\/work1\/src\/com\/base\/work\/action\/product\/ProductSortAction.java"},{"path":"\/work1\/src\/com\/base\/work\/controller","parentWorkspace":"C:\/src\/jspwork","name":"ProductController.java","lastModified":1592208445594,"locationURI":"file:\/C:\/src\/jspwork\/work1\/src\/com\/base\/work\/controller\/ProductController.java"},{"path":"\/work1\/src\/com\/base\/work\/repository","parentWorkspace":"C:\/src\/jspwork","name":"ProductRepository.java","lastModified":1592212955179,"locationURI":"file:\/C:\/src\/jspwork\/work1\/src\/com\/base\/work\/repository\/ProductRepository.java"},{"path":"\/work1\/src\/com\/base\/work\/model","parentWorkspace":"C:\/src\/jspwork","name":"ProductType.java","lastModified":1592199618264,"locationURI":"file:\/C:\/src\/jspwork\/work1\/src\/com\/base\/work\/model\/ProductType.java"},{"path":"\/work1\/WebContent","parentWorkspace":"C:\/src\/jspwork","name":"index.jsp","lastModified":1592201575152,"locationURI":"file:\/C:\/src\/jspwork\/work1\/WebContent\/index.jsp"},{"path":"\/work1\/src\/com\/base\/work\/action","parentWorkspace":"C:\/src\/jspwork","name":"Action.java","lastModified":1592200473841,"locationURI":"file:\/C:\/src\/jspwork\/work1\/src\/com\/base\/work\/action\/Action.java"},{"path":"\/work1\/WebContent\/META-INF","parentWorkspace":"C:\/src\/jspwork","name":"context.xml","lastModified":1592198984289,"locationURI":"file:\/C:\/src\/jspwork\/work1\/WebContent\/META-INF\/context.xml"}]}